<!-- Template for Android Capacitor App Manifest -->
<!-- Copy this content to android/app/src/main/AndroidManifest.xml after running `npx cap add android` -->

<manifest xmlns:android="http://schemas.android.com/apk/res/android"
    package="com.fastnow.zenith">

    <!-- REQUIRED: Add this permission for voice recording functionality -->
    <uses-permission android:name="android.permission.RECORD_AUDIO" />
    
    <!-- Standard Capacitor permissions -->
    <uses-permission android:name="android.permission.INTERNET" />
    <uses-permission android:name="android.permission.READ_EXTERNAL_STORAGE"/>
    <uses-permission android:name="android.permission.WRITE_EXTERNAL_STORAGE" />
    <uses-permission android:name="android.permission.ACCESS_NETWORK_STATE" />
    <uses-permission android:name="android.permission.ACCESS_WIFI_STATE" />
    
    <!-- Optional: Camera permission if you plan to add camera features -->
    <!-- <uses-permission android:name="android.permission.CAMERA" /> -->
    
    <!-- Optional: Location permissions if you plan to add location features -->
    <!-- <uses-permission android:name="android.permission.ACCESS_COARSE_LOCATION" /> -->
    <!-- <uses-permission android:name="android.permission.ACCESS_FINE_LOCATION" /> -->
    
    <application
        android:allowBackup="true"
        android:icon="@mipmap/ic_launcher"
        android:label="@string/app_name"
        android:roundIcon="@mipmap/ic_launcher_round"
        android:supportsRtl="true"
        android:theme="@style/AppTheme"
        android:usesCleartextTraffic="true">

        <activity
            android:exported="true"
            android:launchMode="singleTask"
            android:name="com.fastnow.zenith.MainActivity"
            android:theme="@style/AppTheme.NoActionBarLaunch">

            <intent-filter>
                <action android:name="android.intent.action.MAIN" />
                <category android:name="android.intent.category.LAUNCHER" />
            </intent-filter>

        </activity>

        <provider
            android:name="androidx.core.content.FileProvider"
            android:authorities="${applicationId}.fileprovider"
            android:exported="false"
            android:grantUriPermissions="true">
            <meta-data
                android:name="android.support.FILE_PROVIDER_PATHS"
                android:resource="@xml/file_paths"></meta-data>
        </provider>
    </application>

    <!-- Restrict to phone devices only -->
    <uses-feature android:name="android.hardware.telephony" android:required="false" />
    <uses-feature android:name="android.hardware.microphone" android:required="true" />
    
</manifest>